CognitiveModulePlatform/__init__.py
CognitiveModulePlatform/create_data_medifit.py
CognitiveModulePlatform/data_creation.py
CognitiveModulePlatform/data_preprocessing.py
CognitiveModulePlatform/fusion_1_creation.py
CognitiveModulePlatform/fusion_2_creation.py
CognitiveModulePlatform/fusion_3_creation.py
CognitiveModulePlatform/preprocessing_ftir.py
CognitiveModulePlatform/preprocessing_ftnir.py
CognitiveModulePlatform/preprocessing_raman.py
CognitiveModulePlatform/preprocessing_uvvis.py
CognitiveModulePlatform/raw_data_smoothing_methods.py
FusionEngine/__init__.py
FusionEngine/bayesian_fusion.py
FusionEngine/classification_example.py
FusionEngine/main_adulteration_h_f2.py
FusionEngine/multiclass_classification.py
FusionEngine/occ_example.py
FusionEngine/one_class_classification.py
medifit_fusion_lib-0.1.1.dist-info/METADATA
medifit_fusion_lib-0.1.1.dist-info/WHEEL
medifit_fusion_lib-0.1.1.dist-info/entry_points.txt
medifit_fusion_lib-0.1.1.dist-info/top_level.txt
medifit_fusion_lib-0.1.1.dist-info/RECORD
