Metadata-Version: 2.1
Name: medifit-fusion-lib
Version: 0.1.1
Summary: UNKNOWN
Home-page: https://github.com/MEDIFIT-PRIMA/data_fusion
Author: Antonios Morellos
Author-email: antonios.morellos@gmail.com
License: UNKNOWN
Platform: UNKNOWN
Requires-Python: >=3.9
Requires-Dist: contourpy (==1.1.0)
Requires-Dist: cycler (==0.11.0)
Requires-Dist: et-xmlfile (==1.1.0)
Requires-Dist: fonttools (==4.42.0)
Requires-Dist: importlib-resources (==6.0.1)
Requires-Dist: joblib (==1.3.2)
Requires-Dist: kiwisolver (==1.4.4)
Requires-Dist: matplotlib (==3.7.2)
Requires-Dist: numpy (==1.25.2)
Requires-Dist: openpyxl (==3.1.2)
Requires-Dist: packaging (==23.1)
Requires-Dist: pandas (==2.0.3)
Requires-Dist: Pillow (==10.0.0)
Requires-Dist: pyparsing (==3.0.9)
Requires-Dist: python-dateutil (==2.8.2)
Requires-Dist: pytz (==2023.3)
Requires-Dist: scikit-learn (==1.2.2)
Requires-Dist: scipy (==1.11.1)
Requires-Dist: seaborn (==0.12.2)
Requires-Dist: six (==1.16.0)
Requires-Dist: tabulate (==0.9.0)
Requires-Dist: threadpoolctl (==3.2.0)
Requires-Dist: tzdata (==2023.3)
Requires-Dist: zipp (==3.16.2)
